hnapi/__init__.py
hnapi-0.0.0.dist-info/METADATA
hnapi-0.0.0.dist-info/WHEEL
hnapi-0.0.0.dist-info/top_level.txt
hnapi-0.0.0.dist-info/RECORD
