Metadata-Version: 2.1
Name: hnapi
Version: 0.0.0
Summary: HN API Wrapper
Home-page: https://github.com/IThinkImOKAY/hnapi
Author: diogenesjunior
Author-email: diogenesjunior@protonmail.com
License: UNKNOWN
Keywords: hn hackernews api hacker news
Platform: UNKNOWN
Requires-Dist: requests
